<?xml version="1.0" encoding="UTF-8"?>
<objects serializationModel="Studio.01.09.00">
    <object class="AudioFile" id="{1d940369-e506-4a55-98d7-164f4f1bb758}">
        <property name="assetPath">
            <value>MaJiang/Nan/BaoPai/tiao/5.mp3</value>
        </property>
        <property name="frequencyInKHz">
            <value>44.0999985</value>
        </property>
        <property name="channelCount">
            <value>2</value>
        </property>
        <property name="length">
            <value>0.57469387755102042</value>
        </property>
        <relationship name="masterAssetFolder">
            <destination>{cb84d3cd-d546-47ed-b05b-3b8d367270fe}</destination>
        </relationship>
    </object>
</objects>
