<?xml version="1.0" encoding="UTF-8"?>
<objects serializationModel="Studio.01.09.00">
    <object class="AudioFile" id="{2bed432b-dea3-4492-a7bd-f2a8f8884a13}">
        <property name="assetPath">
            <value>DouDiZhu/Nv/CardNum/12.mp3</value>
        </property>
        <property name="frequencyInKHz">
            <value>44.0999985</value>
        </property>
        <property name="channelCount">
            <value>1</value>
        </property>
        <property name="length">
            <value>2.2987755102040817</value>
        </property>
        <relationship name="masterAssetFolder">
            <destination>{cb84d3cd-d546-47ed-b05b-3b8d367270fe}</destination>
        </relationship>
    </object>
</objects>
